yards/__init__.py
yards/_cli.py
yards/_gui.py
yards/data_generator.py
yards/tools/_helper.py
yards/tools/_validator.py
yards/yards.py
yards-0.1.3.1.dist-info/entry_points.txt
yards-0.1.3.1.dist-info/LICENSE
yards-0.1.3.1.dist-info/WHEEL
yards-0.1.3.1.dist-info/METADATA
yards-0.1.3.1.dist-info/RECORD
