Metadata-Version: 2.1
Name: yards
Version: 0.1.3.1
Summary: 
Author: chanhakim
Author-email: chanhakim17@gmail.com
Requires-Python: >=3.7,<4.0
Classifier: Programming Language :: Python :: 3
Classifier: Programming Language :: Python :: 3.7
Classifier: Programming Language :: Python :: 3.8
Requires-Dist: numpy (>=1.19.0,<2.0.0)
Requires-Dist: pillow (>=7.2.0,<8.0.0)
Requires-Dist: progressbar2 (>=3.51.4,<4.0.0)
Requires-Dist: pyyaml (>=5.3.1,<6.0.0)
Requires-Dist: tqdm (>=4.48.0,<5.0.0)
